grazier/__init__.py
grazier/cli.py
grazier/engines/__init__.py
grazier/engines/default.py
grazier/engines/chat/__init__.py
grazier/engines/chat/anthropic_engine.py
grazier/engines/chat/anthropic_engine_test.py
grazier/engines/chat/bard_engine.py
grazier/engines/chat/bard_engine_test.py
grazier/engines/chat/hf_engine.py
grazier/engines/chat/hf_engine_test.py
grazier/engines/chat/llama_engine.py
grazier/engines/chat/llama_engine_test.py
grazier/engines/chat/openai_engine.py
grazier/engines/chat/openai_engine_test.py
grazier/engines/chat/stable_lm_engine.py
grazier/engines/chat/stable_lm_engine_test.py
grazier/engines/chat/vertex_engine.py
grazier/engines/chat/vertex_engine_test.py
grazier/engines/chat/dolly/__init__.py
grazier/engines/chat/dolly/dolly_engine_test.py
grazier/engines/chat/dolly/instruct_pipeline.py
grazier/engines/image/__init__.py
grazier/engines/image/blip_engine.py
grazier/engines/image/blip_engine_test.py
grazier/engines/image/open_flamingo_engine.py
grazier/engines/image/open_flamingo_engine_test.py
grazier/engines/llm/__init__.py
grazier/engines/llm/ai21_engine.py
grazier/engines/llm/ai21_engine_test.py
grazier/engines/llm/chat_engine.py
grazier/engines/llm/huggingface_engine.py
grazier/engines/llm/huggingface_engine_test.py
grazier/engines/llm/llama_engine.py
grazier/engines/llm/llama_engine_test.py
grazier/engines/llm/openai_engine.py
grazier/engines/llm/openai_engine_test.py
grazier/engines/llm/vertex_engine.py
grazier/engines/llm/vertex_engine_test.py
grazier/utils/__init__.py
grazier/utils/huggingface.py
grazier/utils/python.py
grazier/utils/pytorch.py
grazier/utils/secrets.py
grazier/utils/llama/convert_llama_weights_to_hf.py
grazier/utils/llama/weight_diff.py
grazier-0.1.1.dist-info/LICENSE
grazier-0.1.1.dist-info/METADATA
grazier-0.1.1.dist-info/WHEEL
grazier-0.1.1.dist-info/entry_points.txt
grazier-0.1.1.dist-info/top_level.txt
grazier-0.1.1.dist-info/RECORD
