Metadata-Version: 2.1
Name: grazier
Version: 0.1.1
Summary: A tool for calling (and calling out to) large language models.
Author-email: David Chan <davidchan@berkeley.edu>
License: 
Project-URL: homepage, https://github.com/DavidMChan/grazier
Project-URL: documentation, https://github.com/DavidMChan/grazier
Project-URL: repository, https://github.com/DavidMChan/grazier
Keywords: language-models,api,transformers,huggingface,openai,anthropic,gpt3,gpt-j,gpt-neo,gpt4,vertex,palm,bard
Classifier: License :: OSI Approved :: MIT License
Classifier: Programming Language :: Python :: 3
Classifier: Programming Language :: Python :: 3.8
Classifier: Programming Language :: Python :: 3.9
Classifier: Programming Language :: Python :: 3.10
Classifier: Programming Language :: Python :: 3.11
Classifier: Programming Language :: Python :: 3.12
Classifier: Development Status :: 3 - Alpha
Classifier: Topic :: Scientific/Engineering :: Artificial Intelligence
Classifier: Topic :: Scientific/Engineering :: Human Machine Interfaces
Classifier: Typing :: Typed
Requires-Python: >=3.8.0
License-File: LICENSE
Requires-Dist: click
Requires-Dist: rich
Requires-Dist: python-dotenv
Requires-Dist: ratelimit
Requires-Dist: fire
Requires-Dist: keyring
Requires-Dist: keyrings.cryptfile
Requires-Dist: requests
Requires-Dist: openai <1.0
Requires-Dist: anthropic
Requires-Dist: google-cloud-aiplatform[pipelines]
Requires-Dist: ai21
Requires-Dist: GoogleBard
Requires-Dist: open-flamingo
Requires-Dist: torch >=1.13.0
Requires-Dist: transformers >=4.34
Requires-Dist: bitsandbytes
Requires-Dist: sentencepiece
Requires-Dist: accelerate
Requires-Dist: einops
Requires-Dist: scipy
Requires-Dist: pillow
Provides-Extra: dev
Requires-Dist: pytest ; extra == 'dev'
Requires-Dist: ruff ; extra == 'dev'
Requires-Dist: mypy ; extra == 'dev'
